{
	"credit": "Made with Blockbench",
	"textures": {
		"0": "pipeorgans:block/subbass",
		"particle": "pipeorgans:block/particle/subbass_particle"
	},
	"elements": [
		{
			"from": [2, 0, 2],
			"to": [14, 16, 14],
			"rotation": {"angle": 0, "axis": "y", "origin": [7, 0, 7]},
			"faces": {
				"north": {"uv": [6.25, 4, 7.75, 6], "texture": "#0"},
				"east": {"uv": [6.25, 4, 7.75, 6], "texture": "#0"},
				"south": {"uv": [6.25, 4, 7.75, 6], "texture": "#0"},
				"west": {"uv": [6.25, 4, 7.75, 6], "texture": "#0"}
			}
		},
		{
			"name": "rim_medium",
			"from": [1, 16, 1],
			"to": [15, 18, 15],
			"rotation": {"angle": 0, "axis": "y", "origin": [7, 12, 7]},
			"faces": {
				"north": {"uv": [6.125, 3.75, 7.875, 4], "texture": "#0", "cullface": "up"},
				"east": {"uv": [6.125, 3.75, 7.875, 4], "texture": "#0", "cullface": "up"},
				"south": {"uv": [6.125, 3.75, 7.875, 4], "texture": "#0", "cullface": "up"},
				"west": {"uv": [6.125, 3.75, 7.875, 4], "texture": "#0", "cullface": "up"},
				"up": {"uv": [6.125, 6.125, 7.875, 7.875], "texture": "#0", "cullface": "up"},
				"down": {"uv": [0.125, 14.125, 1.875, 15.875], "texture": "#0", "cullface": "up"}
			}
		}
	]
}